apiconfig/README.md
apiconfig/__init__.py
apiconfig/auth/README.md
apiconfig/auth/__init__.py
apiconfig/auth/base.py
apiconfig/auth/strategies/README.md
apiconfig/auth/strategies/__init__.py
apiconfig/auth/strategies/api_key.py
apiconfig/auth/strategies/basic.py
apiconfig/auth/strategies/bearer.py
apiconfig/auth/strategies/custom.py
apiconfig/auth/token/README.md
apiconfig/auth/token/__init__.py
apiconfig/auth/token/refresh.py
apiconfig/auth/token/storage.py
apiconfig/config/README.md
apiconfig/config/__init__.py
apiconfig/config/base.py
apiconfig/config/manager.py
apiconfig/config/providers/README.md
apiconfig/config/providers/__init__.py
apiconfig/config/providers/env.py
apiconfig/config/providers/file.py
apiconfig/config/providers/memory.py
apiconfig/exceptions/README.md
apiconfig/exceptions/__init__.py
apiconfig/exceptions/auth.py
apiconfig/exceptions/base.py
apiconfig/exceptions/config.py
apiconfig/exceptions/http.py
apiconfig/py.typed
apiconfig/testing/README.md
apiconfig/testing/__init__.py
apiconfig/testing/auth_verification.py
apiconfig/testing/integration/README.md
apiconfig/testing/integration/__init__.py
apiconfig/testing/integration/fixtures.py
apiconfig/testing/integration/helpers.py
apiconfig/testing/integration/servers.py
apiconfig/testing/unit/README.md
apiconfig/testing/unit/__init__.py
apiconfig/testing/unit/assertions.py
apiconfig/testing/unit/factories.py
apiconfig/testing/unit/helpers.py
apiconfig/testing/unit/mocks/README.md
apiconfig/testing/unit/mocks/__init__.py
apiconfig/testing/unit/mocks/auth.py
apiconfig/testing/unit/mocks/config.py
apiconfig/types/README.md
apiconfig/types/__init__.py
apiconfig/types/auth.py
apiconfig/types/config.py
apiconfig/types/extensions.py
apiconfig/types/http.py
apiconfig/types/json.py
apiconfig/utils/README.md
apiconfig/utils/__init__.py
apiconfig/utils/http.py
apiconfig/utils/logging/README.md
apiconfig/utils/logging/__init__.py
apiconfig/utils/logging/filters.py
apiconfig/utils/logging/formatters/README.md
apiconfig-0.3.3.dist-info/COPYING
apiconfig-0.3.3.dist-info/COPYING.LESSER
apiconfig-0.3.3.dist-info/LICENSE
apiconfig-0.3.3.dist-info/METADATA
apiconfig-0.3.3.dist-info/WHEEL
apiconfig-0.3.3.dist-info/RECORD
