Metadata-Version: 2.3
Name: apiconfig
Version: 0.3.3
Summary: api config library
License: LGPL-3.0-or-later
Keywords: api,config,apiauth
Author: Leikaab
Author-email: nordavindltd@gmail.com
Requires-Python: >=3.11,<4.0
Classifier: License :: OSI Approved :: GNU Lesser General Public License v3 or later (LGPLv3+)
Classifier: Programming Language :: Python :: 3
Classifier: Programming Language :: Python :: 3.11
Classifier: Programming Language :: Python :: 3.12
Classifier: Programming Language :: Python :: 3.13
Classifier: Typing :: Typed
Project-URL: Bug Tracker, https://github.com/Leikaab/apiconfig/issues
Project-URL: Documentation, https://leikaab.github.io/apiconfig/
Project-URL: Homepage, https://github.com/Leikaab/apiconfig
Project-URL: Repository, https://github.com/Leikaab/apiconfig
